analytic.py
webanalytictool-0.0.2.dist-info/LICENSE
webanalytictool-0.0.2.dist-info/METADATA
webanalytictool-0.0.2.dist-info/WHEEL
webanalytictool-0.0.2.dist-info/top_level.txt
webanalytictool-0.0.2.dist-info/RECORD
