Metadata-Version: 2.1
Name: webanalytictool
Version: 0.0.2
Summary: A package for analysing webpages
Home-page: https://github.com/komus/webpage-analysis-tool
Author: Oyindolapo Komolafe
Author-email: 
License: UNKNOWN
Platform: UNKNOWN
Classifier: Programming Language :: Python :: 3
Classifier: Programming Language :: Python :: 3.8
Classifier: Programming Language :: Python :: 3.9
Classifier: License :: OSI Approved :: GNU Lesser General Public License v3 (LGPLv3)
Classifier: Operating System :: OS Independent
Requires-Dist: beautifulsoup4 (~=4.9.3)
Requires-Dist: requests (~=2.25.1)
Requires-Dist: pandas (~=1.3.0)
Provides-Extra: dev
Requires-Dist: pytest (>=3.7) ; extra == 'dev'
